[
  {
    "customerId": "123",
    "name": "Bertil",
    "accounts": [
      {
        "accountNumber": "213213213213213",
        "balance": 0.0,
        "interestRate": 0.05,
        "transactions": []
      }
    ]
  },
  {
    "customerId": "6612213211",
    "name": "Albert Herbertsson",
    "accounts": [
      {
        "accountNumber": "112043026497",
        "balance": 0.0,
        "interestRate": 0.05,
        "transactions": []
      }
    ]
  },
  {
    "customerId": "1231231231",
    "name": "Bengan Bongan",
    "personalNumber": "1231231231",
    "address": "billeberga",
    "email": "lksajkdgkjah@sdjfg.se",
    "phone": "656544654654654",
    "accounts": [
      {
        "accountNumber": "903593832347",
        "balance": 0.0,
        "interestRate": 0.015,
        "clearingNumber": "2222-2",
        "transactions": []
      }
    ]
  }
]